fidelius/__init__.py
fidelius/fideliusapi/__init__.py
fidelius/gateway/__init__.py
fidelius/gateway/_abstract.py
fidelius/gateway/interface.py
fidelius/gateway/mock/__init__.py
fidelius/gateway/mock/_inmemcache.py
fidelius/gateway/mock/_mockadmin.py
fidelius/gateway/mock/_mockrepo.py
fidelius/gateway/mock/_std.py
fidelius/gateway/paramstore/__init__.py
fidelius/gateway/paramstore/_paramstoreadmin.py
fidelius/gateway/paramstore/_paramstorerepo.py
fidelius/gateway/paramstore/_std.py
fidelius/gateway/vault/__init__.py
fidelius/gateway/vault/_client.py
fidelius/gateway/vault/_std.py
fidelius/gateway/vault/_structs.py
fidelius/gateway/vault/_vaultadmin.py
fidelius/gateway/vault/_vaultrepo.py
fidelius/structs/__init__.py
fidelius/structs/_appprops.py
fidelius/structs/_base.py
fidelius/structs/_errors.py
fidelius/structs/_tags.py
fidelius/structs/api.py
fidelius/utils/__init__.py
fidelius/utils/_selfresdc.py
fidelius-2.0.1.dist-info/LICENSE
fidelius-2.0.1.dist-info/METADATA
fidelius-2.0.1.dist-info/WHEEL
fidelius-2.0.1.dist-info/top_level.txt
fidelius-2.0.1.dist-info/RECORD
