Metadata-Version: 2.1
Name: fidelius
Version: 2.0.1
Summary: The Fidelius Charm! (keeping things secret)
Author-email: Thordur Matthiasson <thordurm@ccpgames.com>, Kristin Fjola Tomasdottir <kristinf@ccpgames.com>
License: MIT License
Project-URL: Homepage, https://github.com/ccpgames/fidelius
Project-URL: Documentation, https://github.com/ccpgames/fidelius/blob/main/README.md
Project-URL: Repository, https://github.com/ccpgames/fidelius.git
Project-URL: Issues, https://github.com/ccpgames/fidelius/issues
Project-URL: Changelog, https://github.com/ccpgames/fidelius/blob/main/CHANGELOG.md
Keywords: parameter store,aws,secrets,tools,ccp,utils,hashicorp vault
Classifier: Development Status :: 4 - Beta
Classifier: License :: OSI Approved :: MIT License
Classifier: Intended Audience :: Developers
Classifier: Programming Language :: Python
Classifier: Programming Language :: Python :: 3
Classifier: Programming Language :: Python :: 3.8
Classifier: Programming Language :: Python :: 3.9
Classifier: Programming Language :: Python :: 3.10
Classifier: Programming Language :: Python :: 3.11
Classifier: Programming Language :: Python :: 3.12
Classifier: Topic :: Software Development
Classifier: Topic :: Software Development :: Libraries
Classifier: Topic :: Software Development :: Libraries :: Python Modules
Classifier: Topic :: Utilities
License-File: LICENSE
Requires-Dist: ccptools<2,>=1.1
Provides-Extra: aws
Requires-Dist: boto3<2,>=1.20; extra == "aws"
Provides-Extra: vault
Requires-Dist: hvac<3,>=2.2; extra == "vault"
